cluestar/__init__.py
tests/__init__.py
tests/test_smoke.py
cluestar-0.2.1.dist-info/LICENSE
cluestar-0.2.1.dist-info/METADATA
cluestar-0.2.1.dist-info/WHEEL
cluestar-0.2.1.dist-info/top_level.txt
cluestar-0.2.1.dist-info/RECORD
