Metadata-Version: 2.1
Name: cluestar
Version: 0.2.1
Summary: Gain a clue by clustering!
Home-page: https://github.com/koaning/cluestar/
Author: Vincent D. Warmerdam
Project-URL: Documentation, https://github.com/koaning/cluestar/
Project-URL: Source Code, https://github.com/koaning/cluestar/
Project-URL: Issue Tracker, https://github.com/koaning/cluestar/issues
Classifier: Intended Audience :: Science/Research
Classifier: Programming Language :: Python :: 3
Classifier: Programming Language :: Python :: 3.8
Classifier: Programming Language :: Python :: 3.9
Classifier: Programming Language :: Python :: 3.10
Classifier: Programming Language :: Python :: 3.11
Classifier: License :: OSI Approved :: MIT License
Classifier: Topic :: Scientific/Engineering
Classifier: Topic :: Scientific/Engineering :: Artificial Intelligence
License-File: LICENSE
Requires-Dist: altair >=5.0.0
Requires-Dist: numpy >=1.19.2
Provides-Extra: base
Requires-Dist: altair >=5.0.0 ; extra == 'base'
Requires-Dist: numpy >=1.19.2 ; extra == 'base'
Provides-Extra: dev
Requires-Dist: altair >=5.0.0 ; extra == 'dev'
Requires-Dist: numpy >=1.19.2 ; extra == 'dev'
Requires-Dist: pytest >=4.0.2 ; extra == 'dev'
Requires-Dist: black >=19.3b0 ; extra == 'dev'
Requires-Dist: pytest-cov >=2.6.1 ; extra == 'dev'
Requires-Dist: pre-commit >=2.2.0 ; extra == 'dev'
Requires-Dist: jupyterlab ; extra == 'dev'
